pryeact/__init__.py
pryeact/pryeact.py
pryeact-0.0.2.5.dist-info/LICENSE
pryeact-0.0.2.5.dist-info/METADATA
pryeact-0.0.2.5.dist-info/WHEEL
pryeact-0.0.2.5.dist-info/top_level.txt
pryeact-0.0.2.5.dist-info/RECORD
