Metadata-Version: 2.1
Name: pryeact
Version: 0.0.2.5
Summary: Package to componentize interface items created in QT Design.
Home-page: https://github.com/viniciussousa891/pryeact
Author: Vinicius de Sousa Carvalho
Author-email: sousav387@gmail.com
Classifier: Programming Language :: Python :: 3
Classifier: License :: OSI Approved :: MIT License
Classifier: Operating System :: OS Independent
Requires-Python: >=3.8
License-File: LICENSE
